labscript_devices/AlazarTechBoard.py
labscript_devices/Camera.py
labscript_devices/CiceroOpalKellyXEM3001.py
labscript_devices/DummyIntermediateDevice.py
labscript_devices/LightCrafterDMD.py
labscript_devices/NI_PCI_6733.py
labscript_devices/NI_PCIe_6363.py
labscript_devices/NI_USB_6343.py
labscript_devices/NovaTechDDS9M.py
labscript_devices/PhaseMatrixQuickSyn.py
labscript_devices/PineBlaster.py
labscript_devices/PulseBlaster.py
labscript_devices/PulseBlasterESRPro200.py
labscript_devices/PulseBlasterESRPro500.py
labscript_devices/PulseBlasterUSB.py
labscript_devices/PulseBlaster_No_DDS.py
labscript_devices/PulseBlaster_SP2_24_100_32k.py
labscript_devices/PythonCamera.py
labscript_devices/RFBlaster.py
labscript_devices/__init__.py
labscript_devices/__version__.py
labscript_devices/atsapi.py
labscript_devices/camera.ui
labscript_devices/imaqdx_server.py
labscript_devices/phasematrixquicksyn.ui
labscript_devices/pulseblaster.ui
labscript_devices/test_device.py
labscript_devices/AndorSolis/__init__.py
labscript_devices/AndorSolis/blacs_tabs.py
labscript_devices/AndorSolis/blacs_workers.py
labscript_devices/AndorSolis/labscript_devices.py
labscript_devices/AndorSolis/register_classes.py
labscript_devices/AndorSolis/andor_sdk/andor_capabilities.py
labscript_devices/AndorSolis/andor_sdk/andor_solis.py
labscript_devices/AndorSolis/andor_sdk/andor_structures.py
labscript_devices/AndorSolis/andor_sdk/andor_utils.py
labscript_devices/AndorSolis/andor_sdk/status_codes.py
labscript_devices/DummyPseudoclock/__init__.py
labscript_devices/DummyPseudoclock/blacs_tabs.py
labscript_devices/DummyPseudoclock/blacs_workers.py
labscript_devices/DummyPseudoclock/labscript_devices.py
labscript_devices/DummyPseudoclock/register_classes.py
labscript_devices/DummyPseudoclock/runviewer_parsers.py
labscript_devices/FlyCapture2Camera/__init__.py
labscript_devices/FlyCapture2Camera/blacs_tabs.py
labscript_devices/FlyCapture2Camera/blacs_workers.py
labscript_devices-3.2.0.dist-info/LICENSE.txt
labscript_devices-3.2.0.dist-info/METADATA
labscript_devices-3.2.0.dist-info/WHEEL
labscript_devices-3.2.0.dist-info/top_level.txt
labscript_devices-3.2.0.dist-info/RECORD
