Metadata-Version: 2.1
Name: labscript-devices
Version: 3.2.0
Summary: Device drivers for hardware controlled by the labscript suite
Home-page: http://labscriptsuite.org
Author: The labscript suite community
Author-email: labscriptsuite@googlegroups.com
License: BSD
Project-URL: Source Code, https://github.com/labscript-suite/labscript-devices
Project-URL: Download, https://github.com/labscript-suite/labscript-devices/releases
Project-URL: Tracker, https://github.com/labscript-suite/labscript-devices/issues
Keywords: experiment control automation
Classifier: License :: OSI Approved :: BSD License
Classifier: Programming Language :: Python :: 3 :: Only
Classifier: Programming Language :: Python :: 3.6
Classifier: Programming Language :: Python :: 3.7
Classifier: Programming Language :: Python :: 3.8
Classifier: Programming Language :: Python :: 3.9
Classifier: Programming Language :: Python :: 3.10
Classifier: Programming Language :: Python :: 3.11
Requires-Python: >=3.6
License-File: LICENSE.txt
Requires-Dist: blacs (>=3.0.0)
Requires-Dist: runmanager (>=3.0.0)
Requires-Dist: importlib-metadata
Requires-Dist: labscript (>=3.0.0)
Requires-Dist: labscript-utils (>=3.0.0)
Requires-Dist: numpy (>=1.15.1)
Requires-Dist: pillow
Requires-Dist: tqdm
Requires-Dist: PyDAQmx
Requires-Dist: PyVISA
Requires-Dist: PyNIVision
Requires-Dist: pyserial
Requires-Dist: qtutils (>=2.2.3)
Requires-Dist: spinapi
Requires-Dist: zprocess (>=2.18.0)
Provides-Extra: docs
Requires-Dist: PyQt5 ; extra == 'docs'
Requires-Dist: Sphinx (==4.4.0) ; extra == 'docs'
Requires-Dist: sphinx-rtd-theme (==0.5.2) ; extra == 'docs'
Requires-Dist: recommonmark (==0.6.0) ; extra == 'docs'
Requires-Dist: m2r (==0.2.1) ; extra == 'docs'
Requires-Dist: mistune (<2.0.0) ; extra == 'docs'
